
{"items":[{"name":"Документация API","href":"api/PhotoCatalog.Application.Caching.html","tocHref":"api/toc.html","topicHref":"api/PhotoCatalog.Application.Caching.html","topicUid":"PhotoCatalog.Application.Caching"},{"name":"Обучение (Tutorials)","href":"Tutorials/"},{"name":"О проекте","href":"docs/TechnicalSpecification.html","topicHref":"docs/TechnicalSpecification.html"},{"name":"Руководство по Result Fluent API","href":"docs/ResultFluentApi.html","topicHref":"docs/ResultFluentApi.html"}],"pdf":true}
